{
    "CATEGORY": {
        "Perfume": "PF",
        "Cosmetic": "CO",
        "Bath & Body": "BB",
        "Home": "HO",
        "Other": "OT"
    },
    "condition": {
        "Sealed": "SE",
        "Unboxed": "UB",
        "Unsealed": "US",
        "Damaged": "DG",
        "Other": "OT"
    },
    "BRANDS": {
        "Aerin": "AEN",
        "Azzaro": "AZO",
        "Aramis": "ARA",
        "Origins": "AGN",
        "Abercrombie & Fitch": "ABE",
        "Acqua Di Parma": "ACQ",
        "Adam Levine": "ADA",
        "Adidas": "ADI",
        "Aeropostale": "AER",
        "Alaia Paris": "ALA",
        "Alchimie de Rochas": "ALC",
        "Angel Schlesser": "ANG",
        "Armani": "ARM",
        "Atelier Cologne": "ATE",
        "Aveda": "AVE",
        "Balenciaga": "BAL",
        "Banana Republic": "BAN",
        "Bath & Bodyworks": "BAT",
        "Becca": "BEC",
        "Benefit": "BEN",
        "Betsey Johnson": "BET",
        "Bijan": "BIJ",
        "Bioderma": "BIO",
        "Bobbi Brown ": "BOB",
        "Botega Veneta": "BOT",
        "Boucheron": "BOU",
        "British Sterling": "BST",
        "Britney Spears": "BRI",
        "Brooks Brothers": "BRO",
        "Bumble & Bumble": "BUM",
        "Burberry London": "BUR",
        "Bvlgari": "BVL",
        "Cacharel": "CAC",
        "Carolina Herrera": "CHR",
        "Cartier": "CRT",
        "Chanel": "CNL",
        "Chantilly by Dana": "CBD",
        "Chaps": "CHP",
        "Chatecaille": "CHA",
        "Chloe": "CHL",
        "Christian Dior": "CHD",
        "Calvin Klein": "CAL",
        "Clarins Paris": "CLA",
        "Clean": "CLE",
        "Clinique": "CLQ",
        "Coach": "COA",
        "Coqui Coqui": "COQ",
        "COTY": "COT",
        "Creed": "CRD",
        "Creme of Nature": "CRE",
        "Crocodile": "CRO",
        "Curve": "CUR",
        "Danielle Steel": "DAN",
        "Darphin": "DAR",
        "Desigual": "DES",
        "Dior": "DIO",
        "Diptyque": "DIP",
        "Dis-Lui": "DIS",
        "DKNY": "DKN",
        "Dolce & Gabbana": "DNG",
        "Donna Karan": "DON",
        "Dr. Jart": "DRJ",
        "Dr. Jean Marc Pere Formula": "DJM",
        "Dunhill": "DUN",
        "Ed Hardy": "ED ",
        "Elie Saab": "ELS",
        "Elizabeth Arden": "ELI",
        "Estee Lauder": "ESL",
        "Ermenegildo Zegna": "ERM",
        "Fathom": "FAT",
        "FCUK": "FCU",
        "Fekkai": "FEK",
        "Fenty Beauty": "FEN",
        "Frederic Malle": "FML",
        "Fresh": "FRE",
        "Gap": "GAP",
        "Geminelle": "GEM",
        "Givenchy": "GIV",
        "Glamglow ": "GLA",
        "Gucci": "GUC",
        "Guerlain Paris": "GUP",
        "Guess": "GUE",
        "halle berry": "HLB",
        "Halston": "HAL",
        "Hanae mori": "HAN",
        "Harajuku Lovers": "HAR",
        "Hermes Paris": "HER",
        "Hollister ": "HOL",
        "Huda Beauty": "HUD",
        "Hugo": "HUG",
        "Issey Miyake": "ISS",
        "IT COSMETICS": "IT ",
        "J Del Pozo": "J D",
        "Jay Z": "JAY",
        "Jean Paul Gaultier": "JEA",
        "Jessica Simpson": "JES",
        "Jil Sander": "JIL",
        "Jimmy Choo ": "JIM",
        "JLO": "JLO",
        "Jo Malone": "JOM",
        "John Varvatos": "JOH",
        "Juicy Couture": "JUI",
        "Just Cavalli": "JUC",
        "Justin Bieber": "JUS",
        "Kat Von Don": "KVD",
        "Kate Spade": "KSP",
        "Kate Walsh": "KAT",
        "Kenneth cole": "KCL",
        "Kenra": "KEN",
        "Kenzo": "KNZ",
        "Kiehls": "KIE",
        "Kilian": "KIL",
        "Khloé & Lamar": "KHL",
        "La Mer ": "LAM",
        "La Perla": "LAP",
        "La Prairie": "LPR",
        "LAB SERIES": "LAB",
        "Lady Gaga fame": "LAD",
        "Lagerfeld": "LAG",
        "Lancome": "LAN",
        "Laura Mercier": "LAU",
        "Le labo": "LE ",
        "Liz Claiborne": "LIZ",
        "L'Occitane": "L'O",
        "Loreal": "LOR",
        "Loves": "LOV",
        "Lucky": "LUC",
        "m-61": "M-6",
        "Mabonna": "MAB",
        "MAC": "MAC",
        "Maison Margiela": "MAI",
        "Mally + Rupaul": "MAL",
        "Marc ecko": "MEK",
        "Marc Jacobs": "MJC",
        "Marni": "MAR",
        "MCM": "MCM",
        "Michael Kors": "MIC",
        "Milbon": "MIL",
        "Mont Blanc": "MON",
        "Narciso Rodriguez": "NAR",
        "Natasha Denona": "NAT",
        "Nautica": "NAU",
        "Nicki Minaj": "NIC",
        "Nioxin": "NIO",
        "Odori": "ODO",
        "Olay": "OLA",
        "One Direction": "ONE",
        "Paco Rabanne": "PAC",
        "Paloma Picasso": "PAL",
        "Parfum Blaze": "PBZ",
        "Parfum De Chantecaille": "PDC",
        "Parfums Gres": "PAR",
        "Perricone MD": "PMD",
        "Perry Ellis": "PEL",
        "Philosophy": "PHI",
        "Pierre Cardin": "PIE",
        "Prada": "PRA",
        "Prescriptives": "PRE",
        "Professional Sebastian Sharper": "PRO",
        "Paul Sebastian": "PAU",
        "PUIG": "PUI",
        "Quizas": "QUI",
        "R +Co ": "R +",
        "Ralph Lauren": "RAL",
        "Realities": "REA",
        "Revive": "REV",
        "Rihanna": "RIH",
        "Royall": "ROY",
        "Saks Fifth Avenue": "SAK",
        "Salvatore Ferragamo": "SAL",
        "Sean John": "SEA",
        "Serge Lutens": "SER",
        "Shiseido": "SHI",
        "Smashbox": "SMA",
        "Sol De Janeiro": "SOL",
        "Stefano Canturi": "STE",
        "Tarte ": "TAR",
        "Tatiana": "TAT",
        "Thierry Mugler": "THI",
        "Tom Ford": "TOF",
        "Tommy Bahama": "TMB",
        "Tommy Hilfiger": "TMY",
        "Too Faced": "TOO",
        "Tory Burch": "TOR",
        "Tous": "TOU",
        "True Religion": "TRU",
        "United colors of benetton": "UNI",
        "Urban Decay": "URB",
        "Valentino": "VAL",
        "Vanderbilt": "VAN",
        "Versace": "VER",
        "Victoria Secret": "VIC",
        "Viktor & Rolf": "VIK",
        "Vince Camuto": "VIN",
        "Wella": "WEL",
        "Yves Saint Laurent": "YSL"
      }
  }
  